agent_revert/__init__.py
agent_revert/decorators.py
agent_revert-0.1.2.dist-info/METADATA
agent_revert-0.1.2.dist-info/WHEEL
agent_revert-0.1.2.dist-info/top_level.txt
agent_revert-0.1.2.dist-info/RECORD
