Metadata-Version: 2.4
Name: agent-revert
Version: 0.1.2
Summary: A simple decorator for tracking and reverting agent actions
Author-email: Anshul Basia <anshulbasia@alumni.iitd.ac.in>, Siddharth Goyal <goyal.siddharth22@gmail.com>
Maintainer-email: Anshul Basia <anshulbasia@alumni.iitd.ac.in>, Siddharth Goyal <goyal.siddharth22@gmail.com>
License: MIT
Project-URL: Homepage, https://github.com/gateagent/govern
Project-URL: Repository, https://github.com/gateagent/govern
Project-URL: Issues, https://github.com/gateagent/govern
Keywords: agent,tracking,revert,decorator
Classifier: Development Status :: 3 - Alpha
Classifier: Intended Audience :: Developers
Classifier: License :: OSI Approved :: MIT License
Classifier: Programming Language :: Python :: 3
Classifier: Programming Language :: Python :: 3.8
Classifier: Programming Language :: Python :: 3.9
Classifier: Programming Language :: Python :: 3.10
Classifier: Programming Language :: Python :: 3.11
Classifier: Programming Language :: Python :: 3.12
Classifier: Topic :: Software Development :: Libraries :: Python Modules
Requires-Python: >=3.8
Requires-Dist: requests>=2.25.0
Provides-Extra: dev
Requires-Dist: pytest>=7.0.0; extra == "dev"
Requires-Dist: pytest-asyncio>=0.21.0; extra == "dev"
Requires-Dist: black>=23.0.0; extra == "dev"
Requires-Dist: ruff>=0.1.0; extra == "dev"
Requires-Dist: mypy>=1.0.0; extra == "dev"
